spacetimecube/__init__.py
spacetimecube/spacetimecube.py
spacetimecube-1.3.dist-info/METADATA
spacetimecube-1.3.dist-info/WHEEL
spacetimecube-1.3.dist-info/top_level.txt
spacetimecube-1.3.dist-info/RECORD
