Metadata-Version: 2.1
Name: spacetimecube
Version: 1.3
Summary: A plugin for creating Space Time Cube
Home-page: UNKNOWN
Author: Murat Çalışkan, Berk Anbaroğlu
Author-email: caliskan.murat.20@gmail.com,banbar@hacettepe.edu.tr
License: UNKNOWN
Keywords: python,space time cube,getis,ord,local,moran,spatial,data science,gis
Platform: UNKNOWN
Classifier: Development Status :: 5 - Production/Stable
Classifier: Intended Audience :: Science/Research
Classifier: Programming Language :: Python :: 3
Classifier: Operating System :: Unix
Classifier: Operating System :: MacOS :: MacOS X
Classifier: Operating System :: Microsoft :: Windows
Requires-Dist: gdal
Requires-Dist: numpy
Requires-Dist: pandas
Requires-Dist: matplotlib
